[
  {
    "id": "304",
    "name": "Mercury",
    "shortDescription": "The Swiftest Planet",
    "imageUrl": "https://swift-training.s3-eu-west-1.amazonaws.com/Mercury.png",
  },
  {
    "id": "107",
    "name": "Jupiter",
    "shortDescription": "Twice as massive as all the other planets combined",
    "imageUrl": "https://swift-training.s3-eu-west-1.amazonaws.com/Jupiter.png",
  },
  {
    "id": "141",
    "name": "Earth",
    "shortDescription": "Our Home Planet",
    "imageUrl": "https://swift-training.s3-eu-west-1.amazonaws.com/Earth.png",
  }
]
